[
  {
    "session_duration": 0.0006721019744873047,
    "total_messages_sent": 0,
    "total_messages_received": 0,
    "total_bytes_sent": 0,
    "total_bytes_received": 0,
    "total_retransmissions": 0,
    "messages_per_second": 0,
    "bytes_per_second": 0.0,
    "packet_loss_rate": 0,
    "retransmission_rate": 0,
    "timestamp": "2025-06-24T14:37:49.478569"
  },
  {
    "session_duration": 5.001668930053711,
    "total_messages_sent": 1,
    "total_messages_received": 1,
    "total_bytes_sent": 29,
    "total_bytes_received": 16,
    "total_retransmissions": 0,
    "avg_latency_ms": 0,
    "min_latency_ms": 0,
    "max_latency_ms": 0,
    "latency_stddev_ms": 0,
    "jitter_ms": 0,
    "messages_per_second": 0,
    "bytes_per_second": 5.7977584731244995,
    "packet_loss_rate": 0.0,
    "retransmission_rate": 0.0,
    "avg_packet_size": 29,
    "timestamp": "2025-06-24T14:37:54.479916"
  },
  {
    "session_duration": 10.029346942901611,
    "total_messages_sent": 1,
    "total_messages_received": 1,
    "total_bytes_sent": 29,
    "total_bytes_received": 16,
    "total_retransmissions": 0,
    "avg_latency_ms": 0,
    "min_latency_ms": 0,
    "max_latency_ms": 0,
    "latency_stddev_ms": 0,
    "jitter_ms": 0,
    "messages_per_second": 0,
    "bytes_per_second": 2.8914996485432547,
    "packet_loss_rate": 0.0,
    "retransmission_rate": 0.0,
    "avg_packet_size": 29,
    "timestamp": "2025-06-24T14:37:59.507297"
  },
  {
    "session_duration": 15.037313222885132,
    "total_messages_sent": 1,
    "total_messages_received": 1,
    "total_bytes_sent": 29,
    "total_bytes_received": 16,
    "total_retransmissions": 0,
    "avg_latency_ms": 0,
    "min_latency_ms": 0,
    "max_latency_ms": 0,
    "latency_stddev_ms": 0,
    "jitter_ms": 0,
    "messages_per_second": 0,
    "bytes_per_second": 1.9285293412702367,
    "packet_loss_rate": 0.0,
    "retransmission_rate": 0.0,
    "avg_packet_size": 29,
    "timestamp": "2025-06-24T14:38:04.515264"
  },
  {
    "session_duration": 20.049503803253174,
    "total_messages_sent": 1,
    "total_messages_received": 1,
    "total_bytes_sent": 29,
    "total_bytes_received": 16,
    "total_retransmissions": 0,
    "avg_latency_ms": 0,
    "min_latency_ms": 0,
    "max_latency_ms": 0,
    "latency_stddev_ms": 0,
    "jitter_ms": 0,
    "messages_per_second": 0,
    "bytes_per_second": 1.4464163098404297,
    "packet_loss_rate": 0.0,
    "retransmission_rate": 0.0,
    "avg_packet_size": 29,
    "timestamp": "2025-06-24T14:38:09.527451"
  },
  {
    "session_duration": 25.0586678981781,
    "total_messages_sent": 1,
    "total_messages_received": 1,
    "total_bytes_sent": 29,
    "total_bytes_received": 16,
    "total_retransmissions": 0,
    "avg_latency_ms": 0,
    "min_latency_ms": 0,
    "max_latency_ms": 0,
    "latency_stddev_ms": 0,
    "jitter_ms": 0,
    "messages_per_second": 0,
    "bytes_per_second": 1.15728198060374,
    "packet_loss_rate": 0.0,
    "retransmission_rate": 0.0,
    "avg_packet_size": 29,
    "timestamp": "2025-06-24T14:38:14.536613"
  },
  {
    "session_duration": 30.066908359527588,
    "total_messages_sent": 1,
    "total_messages_received": 1,
    "total_bytes_sent": 29,
    "total_bytes_received": 16,
    "total_retransmissions": 0,
    "avg_latency_ms": 0,
    "min_latency_ms": 0,
    "max_latency_ms": 0,
    "latency_stddev_ms": 0,
    "jitter_ms": 0,
    "messages_per_second": 0,
    "bytes_per_second": 0.9645139450958993,
    "packet_loss_rate": 0.0,
    "retransmission_rate": 0.0,
    "avg_packet_size": 29,
    "timestamp": "2025-06-24T14:38:19.544856"
  },
  {
    "session_duration": 35.0761342048645,
    "total_messages_sent": 1,
    "total_messages_received": 1,
    "total_bytes_sent": 29,
    "total_bytes_received": 16,
    "total_retransmissions": 0,
    "avg_latency_ms": 0,
    "min_latency_ms": 0,
    "max_latency_ms": 0,
    "latency_stddev_ms": 0,
    "jitter_ms": 0,
    "messages_per_second": 0,
    "bytes_per_second": 0.8267694675922158,
    "packet_loss_rate": 0.0,
    "retransmission_rate": 0.0,
    "avg_packet_size": 29,
    "timestamp": "2025-06-24T14:38:24.554227"
  },
  {
    "session_duration": 40.108121395111084,
    "total_messages_sent": 1,
    "total_messages_received": 1,
    "total_bytes_sent": 29,
    "total_bytes_received": 16,
    "total_retransmissions": 0,
    "avg_latency_ms": 0,
    "min_latency_ms": 0,
    "max_latency_ms": 0,
    "latency_stddev_ms": 0,
    "jitter_ms": 0,
    "messages_per_second": 0,
    "bytes_per_second": 0.7230440008859034,
    "packet_loss_rate": 0.0,
    "retransmission_rate": 0.0,
    "avg_packet_size": 29,
    "timestamp": "2025-06-24T14:38:29.586107"
  },
  {
    "session_duration": 45.11762881278992,
    "total_messages_sent": 1,
    "total_messages_received": 1,
    "total_bytes_sent": 29,
    "total_bytes_received": 16,
    "total_retransmissions": 0,
    "avg_latency_ms": 0,
    "min_latency_ms": 0,
    "max_latency_ms": 0,
    "latency_stddev_ms": 0,
    "jitter_ms": 0,
    "messages_per_second": 0,
    "bytes_per_second": 0.6427621085565043,
    "packet_loss_rate": 0.0,
    "retransmission_rate": 0.0,
    "avg_packet_size": 29,
    "timestamp": "2025-06-24T14:38:34.595724"
  },
  {
    "session_duration": 50.14997625350952,
    "total_messages_sent": 1,
    "total_messages_received": 1,
    "total_bytes_sent": 29,
    "total_bytes_received": 16,
    "total_retransmissions": 0,
    "avg_latency_ms": 0,
    "min_latency_ms": 0,
    "max_latency_ms": 0,
    "latency_stddev_ms": 0,
    "jitter_ms": 0,
    "messages_per_second": 0,
    "bytes_per_second": 0.5782644857635927,
    "packet_loss_rate": 0.0,
    "retransmission_rate": 0.0,
    "avg_packet_size": 29,
    "timestamp": "2025-06-24T14:38:39.627961"
  },
  {
    "session_duration": 55.15765142440796,
    "total_messages_sent": 1,
    "total_messages_received": 1,
    "total_bytes_sent": 29,
    "total_bytes_received": 16,
    "total_retransmissions": 0,
    "avg_latency_ms": 0,
    "min_latency_ms": 0,
    "max_latency_ms": 0,
    "latency_stddev_ms": 0,
    "jitter_ms": 0,
    "messages_per_second": 0,
    "bytes_per_second": 0.5257652166943311,
    "packet_loss_rate": 0.0,
    "retransmission_rate": 0.0,
    "avg_packet_size": 29,
    "timestamp": "2025-06-24T14:38:44.635603"
  },
  {
    "session_duration": 60.160467863082886,
    "total_messages_sent": 1,
    "total_messages_received": 1,
    "total_bytes_sent": 29,
    "total_bytes_received": 16,
    "total_retransmissions": 0,
    "avg_latency_ms": 0,
    "min_latency_ms": 0,
    "max_latency_ms": 0,
    "latency_stddev_ms": 0,
    "jitter_ms": 0,
    "messages_per_second": 0,
    "bytes_per_second": 0.4820434968952504,
    "packet_loss_rate": 0.0,
    "retransmission_rate": 0.0,
    "avg_packet_size": 29,
    "timestamp": "2025-06-24T14:38:49.638454"
  },
  {
    "session_duration": 65.17333245277405,
    "total_messages_sent": 1,
    "total_messages_received": 1,
    "total_bytes_sent": 29,
    "total_bytes_received": 16,
    "total_retransmissions": 0,
    "avg_latency_ms": 0,
    "min_latency_ms": 0,
    "max_latency_ms": 0,
    "latency_stddev_ms": 0,
    "jitter_ms": 0,
    "messages_per_second": 0,
    "bytes_per_second": 0.4449664702889803,
    "packet_loss_rate": 0.0,
    "retransmission_rate": 0.0,
    "avg_packet_size": 29,
    "timestamp": "2025-06-24T14:38:54.651368"
  },
  {
    "session_duration": 70.19171380996704,
    "total_messages_sent": 1,
    "total_messages_received": 1,
    "total_bytes_sent": 29,
    "total_bytes_received": 16,
    "total_retransmissions": 0,
    "avg_latency_ms": 0,
    "min_latency_ms": 0,
    "max_latency_ms": 0,
    "latency_stddev_ms": 0,
    "jitter_ms": 0,
    "messages_per_second": 0,
    "bytes_per_second": 0.4131534606241025,
    "packet_loss_rate": 0.0,
    "retransmission_rate": 0.0,
    "avg_packet_size": 29,
    "timestamp": "2025-06-24T14:38:59.669763"
  },
  {
    "session_duration": 75.21494507789612,
    "total_messages_sent": 1,
    "total_messages_received": 1,
    "total_bytes_sent": 29,
    "total_bytes_received": 16,
    "total_retransmissions": 0,
    "avg_latency_ms": 0,
    "min_latency_ms": 0,
    "max_latency_ms": 0,
    "latency_stddev_ms": 0,
    "jitter_ms": 0,
    "messages_per_second": 0,
    "bytes_per_second": 0.38556097191853456,
    "packet_loss_rate": 0.0,
    "retransmission_rate": 0.0,
    "avg_packet_size": 29,
    "timestamp": "2025-06-24T14:39:04.693021"
  },
  {
    "session_duration": 80.24529314041138,
    "total_messages_sent": 1,
    "total_messages_received": 1,
    "total_bytes_sent": 29,
    "total_bytes_received": 16,
    "total_retransmissions": 0,
    "avg_latency_ms": 0,
    "min_latency_ms": 0,
    "max_latency_ms": 0,
    "latency_stddev_ms": 0,
    "jitter_ms": 0,
    "messages_per_second": 0,
    "bytes_per_second": 0.36139165426310654,
    "packet_loss_rate": 0.0,
    "retransmission_rate": 0.0,
    "avg_packet_size": 29,
    "timestamp": "2025-06-24T14:39:09.723248"
  },
  {
    "session_duration": 85.25684404373169,
    "total_messages_sent": 1,
    "total_messages_received": 1,
    "total_bytes_sent": 29,
    "total_bytes_received": 16,
    "total_retransmissions": 0,
    "avg_latency_ms": 0,
    "min_latency_ms": 0,
    "max_latency_ms": 0,
    "latency_stddev_ms": 0,
    "jitter_ms": 0,
    "messages_per_second": 0,
    "bytes_per_second": 0.34014836083911065,
    "packet_loss_rate": 0.0,
    "retransmission_rate": 0.0,
    "avg_packet_size": 29,
    "timestamp": "2025-06-24T14:39:14.734821"
  },
  {
    "session_duration": 90.26665472984314,
    "total_messages_sent": 1,
    "total_messages_received": 1,
    "total_bytes_sent": 29,
    "total_bytes_received": 16,
    "total_retransmissions": 0,
    "avg_latency_ms": 0,
    "min_latency_ms": 0,
    "max_latency_ms": 0,
    "latency_stddev_ms": 0,
    "jitter_ms": 0,
    "messages_per_second": 0,
    "bytes_per_second": 0.321270142233521,
    "packet_loss_rate": 0.0,
    "retransmission_rate": 0.0,
    "avg_packet_size": 29,
    "timestamp": "2025-06-24T14:39:19.744613"
  },
  {
    "session_duration": 95.27756428718567,
    "total_messages_sent": 1,
    "total_messages_received": 1,
    "total_bytes_sent": 29,
    "total_bytes_received": 16,
    "total_retransmissions": 0,
    "avg_latency_ms": 0,
    "min_latency_ms": 0,
    "max_latency_ms": 0,
    "latency_stddev_ms": 0,
    "jitter_ms": 0,
    "messages_per_second": 0,
    "bytes_per_second": 0.30437324368290125,
    "packet_loss_rate": 0.0,
    "retransmission_rate": 0.0,
    "avg_packet_size": 29,
    "timestamp": "2025-06-24T14:39:24.755722"
  },
  {
    "session_duration": 100.30147624015808,
    "total_messages_sent": 1,
    "total_messages_received": 1,
    "total_bytes_sent": 29,
    "total_bytes_received": 16,
    "total_retransmissions": 0,
    "avg_latency_ms": 0,
    "min_latency_ms": 0,
    "max_latency_ms": 0,
    "latency_stddev_ms": 0,
    "jitter_ms": 0,
    "messages_per_second": 0,
    "bytes_per_second": 0.28912814261385167,
    "packet_loss_rate": 0.0,
    "retransmission_rate": 0.0,
    "avg_packet_size": 29,
    "timestamp": "2025-06-24T14:39:29.779445"
  },
  {
    "session_duration": 105.31026005744934,
    "total_messages_sent": 1,
    "total_messages_received": 1,
    "total_bytes_sent": 29,
    "total_bytes_received": 16,
    "total_retransmissions": 0,
    "avg_latency_ms": 0,
    "min_latency_ms": 0,
    "max_latency_ms": 0,
    "latency_stddev_ms": 0,
    "jitter_ms": 0,
    "messages_per_second": 0,
    "bytes_per_second": 0.27537639919738893,
    "packet_loss_rate": 0.0,
    "retransmission_rate": 0.0,
    "avg_packet_size": 29,
    "timestamp": "2025-06-24T14:39:34.788349"
  },
  {
    "session_duration": 110.3454806804657,
    "total_messages_sent": 1,
    "total_messages_received": 1,
    "total_bytes_sent": 29,
    "total_bytes_received": 16,
    "total_retransmissions": 0,
    "avg_latency_ms": 0,
    "min_latency_ms": 0,
    "max_latency_ms": 0,
    "latency_stddev_ms": 0,
    "jitter_ms": 0,
    "messages_per_second": 0,
    "bytes_per_second": 0.26281059187899847,
    "packet_loss_rate": 0.0,
    "retransmission_rate": 0.0,
    "avg_packet_size": 29,
    "timestamp": "2025-06-24T14:39:39.823571"
  },
  {
    "session_duration": 115.37887692451477,
    "total_messages_sent": 1,
    "total_messages_received": 1,
    "total_bytes_sent": 29,
    "total_bytes_received": 16,
    "total_retransmissions": 0,
    "avg_latency_ms": 0,
    "min_latency_ms": 0,
    "max_latency_ms": 0,
    "latency_stddev_ms": 0,
    "jitter_ms": 0,
    "messages_per_second": 0,
    "bytes_per_second": 0.2513455152166006,
    "packet_loss_rate": 0.0,
    "retransmission_rate": 0.0,
    "avg_packet_size": 29,
    "timestamp": "2025-06-24T14:39:44.856966"
  },
  {
    "session_duration": 120.41390109062195,
    "total_messages_sent": 1,
    "total_messages_received": 1,
    "total_bytes_sent": 29,
    "total_bytes_received": 16,
    "total_retransmissions": 0,
    "avg_latency_ms": 0,
    "min_latency_ms": 0,
    "max_latency_ms": 0,
    "latency_stddev_ms": 0,
    "jitter_ms": 0,
    "messages_per_second": 0,
    "bytes_per_second": 0.24083585991919762,
    "packet_loss_rate": 0.0,
    "retransmission_rate": 0.0,
    "avg_packet_size": 29,
    "timestamp": "2025-06-24T14:39:49.891862"
  },
  {
    "session_duration": 125.43139553070068,
    "total_messages_sent": 1,
    "total_messages_received": 1,
    "total_bytes_sent": 29,
    "total_bytes_received": 16,
    "total_retransmissions": 0,
    "avg_latency_ms": 0,
    "min_latency_ms": 0,
    "max_latency_ms": 0,
    "latency_stddev_ms": 0,
    "jitter_ms": 0,
    "messages_per_second": 0,
    "bytes_per_second": 0.2312018080904013,
    "packet_loss_rate": 0.0,
    "retransmission_rate": 0.0,
    "avg_packet_size": 29,
    "timestamp": "2025-06-24T14:39:54.909486"
  },
  {
    "session_duration": 130.46544194221497,
    "total_messages_sent": 1,
    "total_messages_received": 1,
    "total_bytes_sent": 29,
    "total_bytes_received": 16,
    "total_retransmissions": 0,
    "avg_latency_ms": 0,
    "min_latency_ms": 0,
    "max_latency_ms": 0,
    "latency_stddev_ms": 0,
    "jitter_ms": 0,
    "messages_per_second": 0,
    "bytes_per_second": 0.22228091893883334,
    "packet_loss_rate": 0.0,
    "retransmission_rate": 0.0,
    "avg_packet_size": 29,
    "timestamp": "2025-06-24T14:39:59.943463"
  },
  {
    "session_duration": 135.48422574996948,
    "total_messages_sent": 1,
    "total_messages_received": 1,
    "total_bytes_sent": 29,
    "total_bytes_received": 16,
    "total_retransmissions": 0,
    "avg_latency_ms": 0,
    "min_latency_ms": 0,
    "max_latency_ms": 0,
    "latency_stddev_ms": 0,
    "jitter_ms": 0,
    "messages_per_second": 0,
    "bytes_per_second": 0.21404698471018907,
    "packet_loss_rate": 0.0,
    "retransmission_rate": 0.0,
    "avg_packet_size": 29,
    "timestamp": "2025-06-24T14:40:04.962170"
  },
  {
    "session_duration": 140.49409556388855,
    "total_messages_sent": 1,
    "total_messages_received": 1,
    "total_bytes_sent": 29,
    "total_bytes_received": 16,
    "total_retransmissions": 0,
    "avg_latency_ms": 0,
    "min_latency_ms": 0,
    "max_latency_ms": 0,
    "latency_stddev_ms": 0,
    "jitter_ms": 0,
    "messages_per_second": 0,
    "bytes_per_second": 0.20641408992532395,
    "packet_loss_rate": 0.0,
    "retransmission_rate": 0.0,
    "avg_packet_size": 29,
    "timestamp": "2025-06-24T14:40:09.972232"
  },
  {
    "session_duration": 145.52820110321045,
    "total_messages_sent": 1,
    "total_messages_received": 1,
    "total_bytes_sent": 29,
    "total_bytes_received": 16,
    "total_retransmissions": 0,
    "avg_latency_ms": 0,
    "min_latency_ms": 0,
    "max_latency_ms": 0,
    "latency_stddev_ms": 0,
    "jitter_ms": 0,
    "messages_per_second": 0,
    "bytes_per_second": 0.19927397909145145,
    "packet_loss_rate": 0.0,
    "retransmission_rate": 0.0,
    "avg_packet_size": 29,
    "timestamp": "2025-06-24T14:40:15.006182"
  },
  {
    "session_duration": 150.53830981254578,
    "total_messages_sent": 1,
    "total_messages_received": 1,
    "total_bytes_sent": 29,
    "total_bytes_received": 16,
    "total_retransmissions": 0,
    "avg_latency_ms": 0,
    "min_latency_ms": 0,
    "max_latency_ms": 0,
    "latency_stddev_ms": 0,
    "jitter_ms": 0,
    "messages_per_second": 0,
    "bytes_per_second": 0.1926418942853362,
    "packet_loss_rate": 0.0,
    "retransmission_rate": 0.0,
    "avg_packet_size": 29,
    "timestamp": "2025-06-24T14:40:20.016295"
  },
  {
    "session_duration": 155.54971313476562,
    "total_messages_sent": 1,
    "total_messages_received": 1,
    "total_bytes_sent": 29,
    "total_bytes_received": 16,
    "total_retransmissions": 0,
    "avg_latency_ms": 0,
    "min_latency_ms": 0,
    "max_latency_ms": 0,
    "latency_stddev_ms": 0,
    "jitter_ms": 0,
    "messages_per_second": 0,
    "bytes_per_second": 0.186435396769481,
    "packet_loss_rate": 0.0,
    "retransmission_rate": 0.0,
    "avg_packet_size": 29,
    "timestamp": "2025-06-24T14:40:25.027805"
  },
  {
    "session_duration": 160.58942985534668,
    "total_messages_sent": 1,
    "total_messages_received": 1,
    "total_bytes_sent": 29,
    "total_bytes_received": 16,
    "total_retransmissions": 0,
    "avg_latency_ms": 0,
    "min_latency_ms": 0,
    "max_latency_ms": 0,
    "latency_stddev_ms": 0,
    "jitter_ms": 0,
    "messages_per_second": 0,
    "bytes_per_second": 0.18058462092038,
    "packet_loss_rate": 0.0,
    "retransmission_rate": 0.0,
    "avg_packet_size": 29,
    "timestamp": "2025-06-24T14:40:30.067434"
  },
  {
    "session_duration": 165.59867882728577,
    "total_messages_sent": 1,
    "total_messages_received": 1,
    "total_bytes_sent": 29,
    "total_bytes_received": 16,
    "total_retransmissions": 0,
    "avg_latency_ms": 0,
    "min_latency_ms": 0,
    "max_latency_ms": 0,
    "latency_stddev_ms": 0,
    "jitter_ms": 0,
    "messages_per_second": 0,
    "bytes_per_second": 0.17512201830629165,
    "packet_loss_rate": 0.0,
    "retransmission_rate": 0.0,
    "avg_packet_size": 29,
    "timestamp": "2025-06-24T14:40:35.076765"
  },
  {
    "session_duration": 170.63562631607056,
    "total_messages_sent": 1,
    "total_messages_received": 1,
    "total_bytes_sent": 29,
    "total_bytes_received": 16,
    "total_retransmissions": 0,
    "avg_latency_ms": 0,
    "min_latency_ms": 0,
    "max_latency_ms": 0,
    "latency_stddev_ms": 0,
    "jitter_ms": 0,
    "messages_per_second": 0,
    "bytes_per_second": 0.16995273516953804,
    "packet_loss_rate": 0.0,
    "retransmission_rate": 0.0,
    "avg_packet_size": 29,
    "timestamp": "2025-06-24T14:40:40.113575"
  },
  {
    "session_duration": 175.64549160003662,
    "total_messages_sent": 1,
    "total_messages_received": 1,
    "total_bytes_sent": 29,
    "total_bytes_received": 16,
    "total_retransmissions": 0,
    "avg_latency_ms": 0,
    "min_latency_ms": 0,
    "max_latency_ms": 0,
    "latency_stddev_ms": 0,
    "jitter_ms": 0,
    "messages_per_second": 0,
    "bytes_per_second": 0.16510515158307418,
    "packet_loss_rate": 0.0,
    "retransmission_rate": 0.0,
    "avg_packet_size": 29,
    "timestamp": "2025-06-24T14:40:45.123584"
  },
  {
    "session_duration": 180.68328523635864,
    "total_messages_sent": 1,
    "total_messages_received": 1,
    "total_bytes_sent": 29,
    "total_bytes_received": 16,
    "total_retransmissions": 0,
    "avg_latency_ms": 0,
    "min_latency_ms": 0,
    "max_latency_ms": 0,
    "latency_stddev_ms": 0,
    "jitter_ms": 0,
    "messages_per_second": 0,
    "bytes_per_second": 0.16050171522604242,
    "packet_loss_rate": 0.0,
    "retransmission_rate": 0.0,
    "avg_packet_size": 29,
    "timestamp": "2025-06-24T14:40:50.161366"
  },
  {
    "session_duration": 185.7156422138214,
    "total_messages_sent": 1,
    "total_messages_received": 1,
    "total_bytes_sent": 29,
    "total_bytes_received": 16,
    "total_retransmissions": 0,
    "avg_latency_ms": 0,
    "min_latency_ms": 0,
    "max_latency_ms": 0,
    "latency_stddev_ms": 0,
    "jitter_ms": 0,
    "messages_per_second": 0,
    "bytes_per_second": 0.156152626996135,
    "packet_loss_rate": 0.0,
    "retransmission_rate": 0.0,
    "avg_packet_size": 29,
    "timestamp": "2025-06-24T14:40:55.193649"
  },
  {
    "session_duration": 190.72799229621887,
    "total_messages_sent": 1,
    "total_messages_received": 1,
    "total_bytes_sent": 29,
    "total_bytes_received": 16,
    "total_retransmissions": 0,
    "avg_latency_ms": 0,
    "min_latency_ms": 0,
    "max_latency_ms": 0,
    "latency_stddev_ms": 0,
    "jitter_ms": 0,
    "messages_per_second": 0,
    "bytes_per_second": 0.15204895860118797,
    "packet_loss_rate": 0.0,
    "retransmission_rate": 0.0,
    "avg_packet_size": 29,
    "timestamp": "2025-06-24T14:41:00.205937"
  },
  {
    "session_duration": 195.7374505996704,
    "total_messages_sent": 1,
    "total_messages_received": 1,
    "total_bytes_sent": 29,
    "total_bytes_received": 16,
    "total_retransmissions": 0,
    "avg_latency_ms": 0,
    "min_latency_ms": 0,
    "max_latency_ms": 0,
    "latency_stddev_ms": 0,
    "jitter_ms": 0,
    "messages_per_second": 0,
    "bytes_per_second": 0.1481576085374245,
    "packet_loss_rate": 0.0,
    "retransmission_rate": 0.0,
    "avg_packet_size": 29,
    "timestamp": "2025-06-24T14:41:05.215399"
  },
  {
    "session_duration": 200.74851322174072,
    "total_messages_sent": 1,
    "total_messages_received": 1,
    "total_bytes_sent": 29,
    "total_bytes_received": 16,
    "total_retransmissions": 0,
    "avg_latency_ms": 0,
    "min_latency_ms": 0,
    "max_latency_ms": 0,
    "latency_stddev_ms": 0,
    "jitter_ms": 0,
    "messages_per_second": 0,
    "bytes_per_second": 0.14445929522529247,
    "packet_loss_rate": 0.0,
    "retransmission_rate": 0.0,
    "avg_packet_size": 29,
    "timestamp": "2025-06-24T14:41:10.226506"
  },
  {
    "session_duration": 205.75168466567993,
    "total_messages_sent": 1,
    "total_messages_received": 1,
    "total_bytes_sent": 29,
    "total_bytes_received": 16,
    "total_retransmissions": 0,
    "avg_latency_ms": 0,
    "min_latency_ms": 0,
    "max_latency_ms": 0,
    "latency_stddev_ms": 0,
    "jitter_ms": 0,
    "messages_per_second": 0,
    "bytes_per_second": 0.14094646234360167,
    "packet_loss_rate": 0.0,
    "retransmission_rate": 0.0,
    "avg_packet_size": 29,
    "timestamp": "2025-06-24T14:41:15.229859"
  },
  {
    "session_duration": 210.7993507385254,
    "total_messages_sent": 1,
    "total_messages_received": 1,
    "total_bytes_sent": 29,
    "total_bytes_received": 16,
    "total_retransmissions": 0,
    "avg_latency_ms": 0,
    "min_latency_ms": 0,
    "max_latency_ms": 0,
    "latency_stddev_ms": 0,
    "jitter_ms": 0,
    "messages_per_second": 0,
    "bytes_per_second": 0.13757154869443747,
    "packet_loss_rate": 0.0,
    "retransmission_rate": 0.0,
    "avg_packet_size": 29,
    "timestamp": "2025-06-24T14:41:20.277298"
  },
  {
    "session_duration": 215.8109803199768,
    "total_messages_sent": 1,
    "total_messages_received": 1,
    "total_bytes_sent": 29,
    "total_bytes_received": 16,
    "total_retransmissions": 0,
    "avg_latency_ms": 0,
    "min_latency_ms": 0,
    "max_latency_ms": 0,
    "latency_stddev_ms": 0,
    "jitter_ms": 0,
    "messages_per_second": 0,
    "bytes_per_second": 0.1343766769629248,
    "packet_loss_rate": 0.0,
    "retransmission_rate": 0.0,
    "avg_packet_size": 29,
    "timestamp": "2025-06-24T14:41:25.289254"
  },
  {
    "session_duration": 220.835844039917,
    "total_messages_sent": 1,
    "total_messages_received": 1,
    "total_bytes_sent": 29,
    "total_bytes_received": 16,
    "total_retransmissions": 0,
    "avg_latency_ms": 0,
    "min_latency_ms": 0,
    "max_latency_ms": 0,
    "latency_stddev_ms": 0,
    "jitter_ms": 0,
    "messages_per_second": 0,
    "bytes_per_second": 0.13131917013068486,
    "packet_loss_rate": 0.0,
    "retransmission_rate": 0.0,
    "avg_packet_size": 29,
    "timestamp": "2025-06-24T14:41:30.313940"
  },
  {
    "session_duration": 225.87315106391907,
    "total_messages_sent": 1,
    "total_messages_received": 1,
    "total_bytes_sent": 29,
    "total_bytes_received": 16,
    "total_retransmissions": 0,
    "avg_latency_ms": 0,
    "min_latency_ms": 0,
    "max_latency_ms": 0,
    "latency_stddev_ms": 0,
    "jitter_ms": 0,
    "messages_per_second": 0,
    "bytes_per_second": 0.1283905521126249,
    "packet_loss_rate": 0.0,
    "retransmission_rate": 0.0,
    "avg_packet_size": 29,
    "timestamp": "2025-06-24T14:41:35.351261"
  },
  {
    "session_duration": 230.90207982063293,
    "total_messages_sent": 1,
    "total_messages_received": 1,
    "total_bytes_sent": 29,
    "total_bytes_received": 16,
    "total_retransmissions": 0,
    "avg_latency_ms": 0,
    "min_latency_ms": 0,
    "max_latency_ms": 0,
    "latency_stddev_ms": 0,
    "jitter_ms": 0,
    "messages_per_second": 0,
    "bytes_per_second": 0.1255943356812132,
    "packet_loss_rate": 0.0,
    "retransmission_rate": 0.0,
    "avg_packet_size": 29,
    "timestamp": "2025-06-24T14:41:40.380031"
  },
  {
    "session_duration": 235.91368579864502,
    "total_messages_sent": 1,
    "total_messages_received": 1,
    "total_bytes_sent": 29,
    "total_bytes_received": 16,
    "total_retransmissions": 0,
    "avg_latency_ms": 0,
    "min_latency_ms": 0,
    "max_latency_ms": 0,
    "latency_stddev_ms": 0,
    "jitter_ms": 0,
    "messages_per_second": 0,
    "bytes_per_second": 0.12292623899290556,
    "packet_loss_rate": 0.0,
    "retransmission_rate": 0.0,
    "avg_packet_size": 29,
    "timestamp": "2025-06-24T14:41:45.391775"
  },
  {
    "session_duration": 240.95207142829895,
    "total_messages_sent": 1,
    "total_messages_received": 1,
    "total_bytes_sent": 29,
    "total_bytes_received": 16,
    "total_retransmissions": 0,
    "avg_latency_ms": 0,
    "min_latency_ms": 0,
    "max_latency_ms": 0,
    "latency_stddev_ms": 0,
    "jitter_ms": 0,
    "messages_per_second": 0,
    "bytes_per_second": 0.12035586189562952,
    "packet_loss_rate": 0.0,
    "retransmission_rate": 0.0,
    "avg_packet_size": 29,
    "timestamp": "2025-06-24T14:41:50.430016"
  },
  {
    "session_duration": 245.96229147911072,
    "total_messages_sent": 1,
    "total_messages_received": 1,
    "total_bytes_sent": 29,
    "total_bytes_received": 16,
    "total_retransmissions": 0,
    "avg_latency_ms": 0,
    "min_latency_ms": 0,
    "max_latency_ms": 0,
    "latency_stddev_ms": 0,
    "jitter_ms": 0,
    "messages_per_second": 0,
    "bytes_per_second": 0.11790422721147797,
    "packet_loss_rate": 0.0,
    "retransmission_rate": 0.0,
    "avg_packet_size": 29,
    "timestamp": "2025-06-24T14:41:55.440241"
  },
  {
    "session_duration": 250.97347402572632,
    "total_messages_sent": 1,
    "total_messages_received": 1,
    "total_bytes_sent": 29,
    "total_bytes_received": 16,
    "total_retransmissions": 0,
    "avg_latency_ms": 0,
    "min_latency_ms": 0,
    "max_latency_ms": 0,
    "latency_stddev_ms": 0,
    "jitter_ms": 0,
    "messages_per_second": 0,
    "bytes_per_second": 0.1155499874039066,
    "packet_loss_rate": 0.0,
    "retransmission_rate": 0.0,
    "avg_packet_size": 29,
    "timestamp": "2025-06-24T14:42:00.451574"
  },
  {
    "session_duration": 256.01076221466064,
    "total_messages_sent": 1,
    "total_messages_received": 1,
    "total_bytes_sent": 29,
    "total_bytes_received": 16,
    "total_retransmissions": 0,
    "avg_latency_ms": 0,
    "min_latency_ms": 0,
    "max_latency_ms": 0,
    "latency_stddev_ms": 0,
    "jitter_ms": 0,
    "messages_per_second": 0,
    "bytes_per_second": 0.11327642309529493,
    "packet_loss_rate": 0.0,
    "retransmission_rate": 0.0,
    "avg_packet_size": 29,
    "timestamp": "2025-06-24T14:42:05.488854"
  },
  {
    "session_duration": 261.02512550354004,
    "total_messages_sent": 1,
    "total_messages_received": 1,
    "total_bytes_sent": 29,
    "total_bytes_received": 16,
    "total_retransmissions": 0,
    "avg_latency_ms": 0,
    "min_latency_ms": 0,
    "max_latency_ms": 0,
    "latency_stddev_ms": 0,
    "jitter_ms": 0,
    "messages_per_second": 0,
    "bytes_per_second": 0.11110038889222998,
    "packet_loss_rate": 0.0,
    "retransmission_rate": 0.0,
    "avg_packet_size": 29,
    "timestamp": "2025-06-24T14:42:10.503088"
  },
  {
    "session_duration": 266.03546953201294,
    "total_messages_sent": 1,
    "total_messages_received": 1,
    "total_bytes_sent": 29,
    "total_bytes_received": 16,
    "total_retransmissions": 0,
    "avg_latency_ms": 0,
    "min_latency_ms": 0,
    "max_latency_ms": 0,
    "latency_stddev_ms": 0,
    "jitter_ms": 0,
    "messages_per_second": 0,
    "bytes_per_second": 0.10900800088480557,
    "packet_loss_rate": 0.0,
    "retransmission_rate": 0.0,
    "avg_packet_size": 29,
    "timestamp": "2025-06-24T14:42:15.513417"
  },
  {
    "session_duration": 271.0485110282898,
    "total_messages_sent": 1,
    "total_messages_received": 1,
    "total_bytes_sent": 29,
    "total_bytes_received": 16,
    "total_retransmissions": 0,
    "avg_latency_ms": 0,
    "min_latency_ms": 0,
    "max_latency_ms": 0,
    "latency_stddev_ms": 0,
    "jitter_ms": 0,
    "messages_per_second": 0,
    "bytes_per_second": 0.10699186514817981,
    "packet_loss_rate": 0.0,
    "retransmission_rate": 0.0,
    "avg_packet_size": 29,
    "timestamp": "2025-06-24T14:42:20.526606"
  },
  {
    "session_duration": 276.0695447921753,
    "total_messages_sent": 1,
    "total_messages_received": 1,
    "total_bytes_sent": 29,
    "total_bytes_received": 16,
    "total_retransmissions": 0,
    "avg_latency_ms": 0,
    "min_latency_ms": 0,
    "max_latency_ms": 0,
    "latency_stddev_ms": 0,
    "jitter_ms": 0,
    "messages_per_second": 0,
    "bytes_per_second": 0.10504593813026956,
    "packet_loss_rate": 0.0,
    "retransmission_rate": 0.0,
    "avg_packet_size": 29,
    "timestamp": "2025-06-24T14:42:25.547637"
  },
  {
    "session_duration": 281.11218523979187,
    "total_messages_sent": 1,
    "total_messages_received": 1,
    "total_bytes_sent": 29,
    "total_bytes_received": 16,
    "total_retransmissions": 0,
    "avg_latency_ms": 0,
    "min_latency_ms": 0,
    "max_latency_ms": 0,
    "latency_stddev_ms": 0,
    "jitter_ms": 0,
    "messages_per_second": 0,
    "bytes_per_second": 0.10316164295534536,
    "packet_loss_rate": 0.0,
    "retransmission_rate": 0.0,
    "avg_packet_size": 29,
    "timestamp": "2025-06-24T14:42:30.590132"
  },
  {
    "session_duration": 286.12390542030334,
    "total_messages_sent": 1,
    "total_messages_received": 1,
    "total_bytes_sent": 29,
    "total_bytes_received": 16,
    "total_retransmissions": 0,
    "avg_latency_ms": 0,
    "min_latency_ms": 0,
    "max_latency_ms": 0,
    "latency_stddev_ms": 0,
    "jitter_ms": 0,
    "messages_per_second": 0,
    "bytes_per_second": 0.10135463923758804,
    "packet_loss_rate": 0.0,
    "retransmission_rate": 0.0,
    "avg_packet_size": 29,
    "timestamp": "2025-06-24T14:42:35.601998"
  },
  {
    "session_duration": 291.1666476726532,
    "total_messages_sent": 1,
    "total_messages_received": 1,
    "total_bytes_sent": 29,
    "total_bytes_received": 16,
    "total_retransmissions": 0,
    "avg_latency_ms": 0,
    "min_latency_ms": 0,
    "max_latency_ms": 0,
    "latency_stddev_ms": 0,
    "jitter_ms": 0,
    "messages_per_second": 0,
    "bytes_per_second": 0.09959928975605054,
    "packet_loss_rate": 0.0,
    "retransmission_rate": 0.0,
    "avg_packet_size": 29,
    "timestamp": "2025-06-24T14:42:40.644652"
  },
  {
    "session_duration": 296.1932964324951,
    "total_messages_sent": 1,
    "total_messages_received": 1,
    "total_bytes_sent": 29,
    "total_bytes_received": 16,
    "total_retransmissions": 0,
    "avg_latency_ms": 0,
    "min_latency_ms": 0,
    "max_latency_ms": 0,
    "latency_stddev_ms": 0,
    "jitter_ms": 0,
    "messages_per_second": 0,
    "bytes_per_second": 0.0979090072114844,
    "packet_loss_rate": 0.0,
    "retransmission_rate": 0.0,
    "avg_packet_size": 29,
    "timestamp": "2025-06-24T14:42:45.671296"
  },
  {
    "session_duration": 301.23080682754517,
    "total_messages_sent": 1,
    "total_messages_received": 1,
    "total_bytes_sent": 29,
    "total_bytes_received": 16,
    "total_retransmissions": 0,
    "avg_latency_ms": 0,
    "min_latency_ms": 0,
    "max_latency_ms": 0,
    "latency_stddev_ms": 0,
    "jitter_ms": 0,
    "messages_per_second": 0,
    "bytes_per_second": 0.09627164915497481,
    "packet_loss_rate": 0.0,
    "retransmission_rate": 0.0,
    "avg_packet_size": 29,
    "timestamp": "2025-06-24T14:42:50.708885"
  },
  {
    "session_duration": 306.26613998413086,
    "total_messages_sent": 1,
    "total_messages_received": 1,
    "total_bytes_sent": 29,
    "total_bytes_received": 16,
    "total_retransmissions": 0,
    "avg_latency_ms": 0,
    "min_latency_ms": 0,
    "max_latency_ms": 0,
    "latency_stddev_ms": 0,
    "jitter_ms": 0,
    "messages_per_second": 0,
    "bytes_per_second": 0.09468887207358882,
    "packet_loss_rate": 0.0,
    "retransmission_rate": 0.0,
    "avg_packet_size": 29,
    "timestamp": "2025-06-24T14:42:55.744086"
  },
  {
    "session_duration": 311.27779936790466,
    "total_messages_sent": 1,
    "total_messages_received": 1,
    "total_bytes_sent": 29,
    "total_bytes_received": 16,
    "total_retransmissions": 0,
    "avg_latency_ms": 0,
    "min_latency_ms": 0,
    "max_latency_ms": 0,
    "latency_stddev_ms": 0,
    "jitter_ms": 0,
    "messages_per_second": 0,
    "bytes_per_second": 0.09316431589001961,
    "packet_loss_rate": 0.0,
    "retransmission_rate": 0.0,
    "avg_packet_size": 29,
    "timestamp": "2025-06-24T14:43:00.755901"
  },
  {
    "session_duration": 316.28937816619873,
    "total_messages_sent": 1,
    "total_messages_received": 1,
    "total_bytes_sent": 29,
    "total_bytes_received": 16,
    "total_retransmissions": 0,
    "avg_latency_ms": 0,
    "min_latency_ms": 0,
    "max_latency_ms": 0,
    "latency_stddev_ms": 0,
    "jitter_ms": 0,
    "messages_per_second": 0,
    "bytes_per_second": 0.09168816640017094,
    "packet_loss_rate": 0.0,
    "retransmission_rate": 0.0,
    "avg_packet_size": 29,
    "timestamp": "2025-06-24T14:43:05.767358"
  },
  {
    "session_duration": 321.3151183128357,
    "total_messages_sent": 1,
    "total_messages_received": 1,
    "total_bytes_sent": 29,
    "total_bytes_received": 16,
    "total_retransmissions": 0,
    "avg_latency_ms": 0,
    "min_latency_ms": 0,
    "max_latency_ms": 0,
    "latency_stddev_ms": 0,
    "jitter_ms": 0,
    "messages_per_second": 0,
    "bytes_per_second": 0.09025404709913774,
    "packet_loss_rate": 0.0,
    "retransmission_rate": 0.0,
    "avg_packet_size": 29,
    "timestamp": "2025-06-24T14:43:10.793157"
  },
  {
    "session_duration": 326.33241176605225,
    "total_messages_sent": 1,
    "total_messages_received": 1,
    "total_bytes_sent": 29,
    "total_bytes_received": 16,
    "total_retransmissions": 0,
    "avg_latency_ms": 0,
    "min_latency_ms": 0,
    "max_latency_ms": 0,
    "latency_stddev_ms": 0,
    "jitter_ms": 0,
    "messages_per_second": 0,
    "bytes_per_second": 0.0888664239385746,
    "packet_loss_rate": 0.0,
    "retransmission_rate": 0.0,
    "avg_packet_size": 29,
    "timestamp": "2025-06-24T14:43:15.810375"
  },
  {
    "session_duration": 331.34381103515625,
    "total_messages_sent": 1,
    "total_messages_received": 1,
    "total_bytes_sent": 29,
    "total_bytes_received": 16,
    "total_retransmissions": 0,
    "avg_latency_ms": 0,
    "min_latency_ms": 0,
    "max_latency_ms": 0,
    "latency_stddev_ms": 0,
    "jitter_ms": 0,
    "messages_per_second": 0,
    "bytes_per_second": 0.08752237060353964,
    "packet_loss_rate": 0.0,
    "retransmission_rate": 0.0,
    "avg_packet_size": 29,
    "timestamp": "2025-06-24T14:43:20.821757"
  },
  {
    "session_duration": 336.356449842453,
    "total_messages_sent": 1,
    "total_messages_received": 1,
    "total_bytes_sent": 29,
    "total_bytes_received": 16,
    "total_retransmissions": 0,
    "avg_latency_ms": 0,
    "min_latency_ms": 0,
    "max_latency_ms": 0,
    "latency_stddev_ms": 0,
    "jitter_ms": 0,
    "messages_per_second": 0,
    "bytes_per_second": 0.08621804246531842,
    "packet_loss_rate": 0.0,
    "retransmission_rate": 0.0,
    "avg_packet_size": 29,
    "timestamp": "2025-06-24T14:43:25.834410"
  },
  {
    "session_duration": 341.3675947189331,
    "total_messages_sent": 1,
    "total_messages_received": 1,
    "total_bytes_sent": 29,
    "total_bytes_received": 16,
    "total_retransmissions": 0,
    "avg_latency_ms": 0,
    "min_latency_ms": 0,
    "max_latency_ms": 0,
    "latency_stddev_ms": 0,
    "jitter_ms": 0,
    "messages_per_second": 0,
    "bytes_per_second": 0.08495239336034109,
    "packet_loss_rate": 0.0,
    "retransmission_rate": 0.0,
    "avg_packet_size": 29,
    "timestamp": "2025-06-24T14:43:30.845569"
  },
  {
    "session_duration": 346.384015083313,
    "total_messages_sent": 1,
    "total_messages_received": 1,
    "total_bytes_sent": 29,
    "total_bytes_received": 16,
    "total_retransmissions": 0,
    "avg_latency_ms": 0,
    "min_latency_ms": 0,
    "max_latency_ms": 0,
    "latency_stddev_ms": 0,
    "jitter_ms": 0,
    "messages_per_second": 0,
    "bytes_per_second": 0.08372207152207432,
    "packet_loss_rate": 0.0,
    "retransmission_rate": 0.0,
    "avg_packet_size": 29,
    "timestamp": "2025-06-24T14:43:35.862094"
  },
  {
    "session_duration": 351.42133498191833,
    "total_messages_sent": 1,
    "total_messages_received": 1,
    "total_bytes_sent": 29,
    "total_bytes_received": 16,
    "total_retransmissions": 0,
    "avg_latency_ms": 0,
    "min_latency_ms": 0,
    "max_latency_ms": 0,
    "latency_stddev_ms": 0,
    "jitter_ms": 0,
    "messages_per_second": 0,
    "bytes_per_second": 0.08252201314751237,
    "packet_loss_rate": 0.0,
    "retransmission_rate": 0.0,
    "avg_packet_size": 29,
    "timestamp": "2025-06-24T14:43:40.899280"
  },
  {
    "session_duration": 356.4319441318512,
    "total_messages_sent": 1,
    "total_messages_received": 1,
    "total_bytes_sent": 29,
    "total_bytes_received": 16,
    "total_retransmissions": 0,
    "avg_latency_ms": 0,
    "min_latency_ms": 0,
    "max_latency_ms": 0,
    "latency_stddev_ms": 0,
    "jitter_ms": 0,
    "messages_per_second": 0,
    "bytes_per_second": 0.08136194304651492,
    "packet_loss_rate": 0.0,
    "retransmission_rate": 0.0,
    "avg_packet_size": 29,
    "timestamp": "2025-06-24T14:43:45.909898"
  },
  {
    "session_duration": 361.44789695739746,
    "total_messages_sent": 1,
    "total_messages_received": 1,
    "total_bytes_sent": 29,
    "total_bytes_received": 16,
    "total_retransmissions": 0,
    "avg_latency_ms": 0,
    "min_latency_ms": 0,
    "max_latency_ms": 0,
    "latency_stddev_ms": 0,
    "jitter_ms": 0,
    "messages_per_second": 0,
    "bytes_per_second": 0.08023285029861042,
    "packet_loss_rate": 0.0,
    "retransmission_rate": 0.0,
    "avg_packet_size": 29,
    "timestamp": "2025-06-24T14:43:50.925857"
  },
  {
    "session_duration": 366.4600429534912,
    "total_messages_sent": 1,
    "total_messages_received": 1,
    "total_bytes_sent": 29,
    "total_bytes_received": 16,
    "total_retransmissions": 0,
    "avg_latency_ms": 0,
    "min_latency_ms": 0,
    "max_latency_ms": 0,
    "latency_stddev_ms": 0,
    "jitter_ms": 0,
    "messages_per_second": 0,
    "bytes_per_second": 0.07913546634689995,
    "packet_loss_rate": 0.0,
    "retransmission_rate": 0.0,
    "avg_packet_size": 29,
    "timestamp": "2025-06-24T14:43:55.938178"
  },
  {
    "session_duration": 371.5028877258301,
    "total_messages_sent": 1,
    "total_messages_received": 1,
    "total_bytes_sent": 29,
    "total_bytes_received": 16,
    "total_retransmissions": 0,
    "avg_latency_ms": 0,
    "min_latency_ms": 0,
    "max_latency_ms": 0,
    "latency_stddev_ms": 0,
    "jitter_ms": 0,
    "messages_per_second": 0,
    "bytes_per_second": 0.07806129401844827,
    "packet_loss_rate": 0.0,
    "retransmission_rate": 0.0,
    "avg_packet_size": 29,
    "timestamp": "2025-06-24T14:44:00.980835"
  },
  {
    "session_duration": 376.51487946510315,
    "total_messages_sent": 1,
    "total_messages_received": 1,
    "total_bytes_sent": 29,
    "total_bytes_received": 16,
    "total_retransmissions": 0,
    "avg_latency_ms": 0,
    "min_latency_ms": 0,
    "max_latency_ms": 0,
    "latency_stddev_ms": 0,
    "jitter_ms": 0,
    "messages_per_second": 0,
    "bytes_per_second": 0.07702217820676856,
    "packet_loss_rate": 0.0,
    "retransmission_rate": 0.0,
    "avg_packet_size": 29,
    "timestamp": "2025-06-24T14:44:05.992827"
  },
  {
    "session_duration": 381.5290422439575,
    "total_messages_sent": 1,
    "total_messages_received": 1,
    "total_bytes_sent": 29,
    "total_bytes_received": 16,
    "total_retransmissions": 0,
    "avg_latency_ms": 0,
    "min_latency_ms": 0,
    "max_latency_ms": 0,
    "latency_stddev_ms": 0,
    "jitter_ms": 0,
    "messages_per_second": 0,
    "bytes_per_second": 0.07600993133448573,
    "packet_loss_rate": 0.0,
    "retransmission_rate": 0.0,
    "avg_packet_size": 29,
    "timestamp": "2025-06-24T14:44:11.006989"
  },
  {
    "session_duration": 386.5415997505188,
    "total_messages_sent": 1,
    "total_messages_received": 1,
    "total_bytes_sent": 29,
    "total_bytes_received": 16,
    "total_retransmissions": 0,
    "avg_latency_ms": 0,
    "min_latency_ms": 0,
    "max_latency_ms": 0,
    "latency_stddev_ms": 0,
    "jitter_ms": 0,
    "messages_per_second": 0,
    "bytes_per_second": 0.07502425157126547,
    "packet_loss_rate": 0.0,
    "retransmission_rate": 0.0,
    "avg_packet_size": 29,
    "timestamp": "2025-06-24T14:44:16.019576"
  },
  {
    "session_duration": 391.5545630455017,
    "total_messages_sent": 1,
    "total_messages_received": 1,
    "total_bytes_sent": 29,
    "total_bytes_received": 16,
    "total_retransmissions": 0,
    "avg_latency_ms": 0,
    "min_latency_ms": 0,
    "max_latency_ms": 0,
    "latency_stddev_ms": 0,
    "jitter_ms": 0,
    "messages_per_second": 0,
    "bytes_per_second": 0.07406370257587347,
    "packet_loss_rate": 0.0,
    "retransmission_rate": 0.0,
    "avg_packet_size": 29,
    "timestamp": "2025-06-24T14:44:21.032738"
  },
  {
    "session_duration": 396.5679099559784,
    "total_messages_sent": 1,
    "total_messages_received": 1,
    "total_bytes_sent": 29,
    "total_bytes_received": 16,
    "total_retransmissions": 0,
    "avg_latency_ms": 0,
    "min_latency_ms": 0,
    "max_latency_ms": 0,
    "latency_stddev_ms": 0,
    "jitter_ms": 0,
    "messages_per_second": 0,
    "bytes_per_second": 0.07312744114569462,
    "packet_loss_rate": 0.0,
    "retransmission_rate": 0.0,
    "avg_packet_size": 29,
    "timestamp": "2025-06-24T14:44:26.045856"
  },
  {
    "session_duration": 401.5800430774689,
    "total_messages_sent": 1,
    "total_messages_received": 1,
    "total_bytes_sent": 29,
    "total_bytes_received": 16,
    "total_retransmissions": 0,
    "avg_latency_ms": 0,
    "min_latency_ms": 0,
    "max_latency_ms": 0,
    "latency_stddev_ms": 0,
    "jitter_ms": 0,
    "messages_per_second": 0,
    "bytes_per_second": 0.07221473519502566,
    "packet_loss_rate": 0.0,
    "retransmission_rate": 0.0,
    "avg_packet_size": 29,
    "timestamp": "2025-06-24T14:44:31.057992"
  },
  {
    "session_duration": 406.592148065567,
    "total_messages_sent": 1,
    "total_messages_received": 1,
    "total_bytes_sent": 29,
    "total_bytes_received": 16,
    "total_retransmissions": 0,
    "avg_latency_ms": 0,
    "min_latency_ms": 0,
    "max_latency_ms": 0,
    "latency_stddev_ms": 0,
    "jitter_ms": 0,
    "messages_per_second": 0,
    "bytes_per_second": 0.07132451071618018,
    "packet_loss_rate": 0.0,
    "retransmission_rate": 0.0,
    "avg_packet_size": 29,
    "timestamp": "2025-06-24T14:44:36.070242"
  },
  {
    "session_duration": 411.6039319038391,
    "total_messages_sent": 1,
    "total_messages_received": 1,
    "total_bytes_sent": 29,
    "total_bytes_received": 16,
    "total_retransmissions": 0,
    "avg_latency_ms": 0,
    "min_latency_ms": 0,
    "max_latency_ms": 0,
    "latency_stddev_ms": 0,
    "jitter_ms": 0,
    "messages_per_second": 0,
    "bytes_per_second": 0.07045607218544048,
    "packet_loss_rate": 0.0,
    "retransmission_rate": 0.0,
    "avg_packet_size": 29,
    "timestamp": "2025-06-24T14:44:41.081883"
  },
  {
    "session_duration": 416.6186637878418,
    "total_messages_sent": 1,
    "total_messages_received": 1,
    "total_bytes_sent": 29,
    "total_bytes_received": 16,
    "total_retransmissions": 0,
    "avg_latency_ms": 0,
    "min_latency_ms": 0,
    "max_latency_ms": 0,
    "latency_stddev_ms": 0,
    "jitter_ms": 0,
    "messages_per_second": 0,
    "bytes_per_second": 0.06960798713840458,
    "packet_loss_rate": 0.0,
    "retransmission_rate": 0.0,
    "avg_packet_size": 29,
    "timestamp": "2025-06-24T14:44:46.096831"
  },
  {
    "session_duration": 421.6556785106659,
    "total_messages_sent": 1,
    "total_messages_received": 1,
    "total_bytes_sent": 29,
    "total_bytes_received": 16,
    "total_retransmissions": 0,
    "avg_latency_ms": 0,
    "min_latency_ms": 0,
    "max_latency_ms": 0,
    "latency_stddev_ms": 0,
    "jitter_ms": 0,
    "messages_per_second": 0,
    "bytes_per_second": 0.06877647701175334,
    "packet_loss_rate": 0.0,
    "retransmission_rate": 0.0,
    "avg_packet_size": 29,
    "timestamp": "2025-06-24T14:44:51.133720"
  },
  {
    "session_duration": 426.6942572593689,
    "total_messages_sent": 1,
    "total_messages_received": 1,
    "total_bytes_sent": 29,
    "total_bytes_received": 16,
    "total_retransmissions": 0,
    "avg_latency_ms": 0,
    "min_latency_ms": 0,
    "max_latency_ms": 0,
    "latency_stddev_ms": 0,
    "jitter_ms": 0,
    "messages_per_second": 0,
    "bytes_per_second": 0.06796432437002402,
    "packet_loss_rate": 0.0,
    "retransmission_rate": 0.0,
    "avg_packet_size": 29,
    "timestamp": "2025-06-24T14:44:56.172379"
  },
  {
    "session_duration": 431.72779393196106,
    "total_messages_sent": 1,
    "total_messages_received": 1,
    "total_bytes_sent": 29,
    "total_bytes_received": 16,
    "total_retransmissions": 0,
    "avg_latency_ms": 0,
    "min_latency_ms": 0,
    "max_latency_ms": 0,
    "latency_stddev_ms": 0,
    "jitter_ms": 0,
    "messages_per_second": 0,
    "bytes_per_second": 0.06717193186580521,
    "packet_loss_rate": 0.0,
    "retransmission_rate": 0.0,
    "avg_packet_size": 29,
    "timestamp": "2025-06-24T14:45:01.205887"
  },
  {
    "session_duration": 436.77556228637695,
    "total_messages_sent": 1,
    "total_messages_received": 1,
    "total_bytes_sent": 29,
    "total_bytes_received": 16,
    "total_retransmissions": 0,
    "avg_latency_ms": 0,
    "min_latency_ms": 0,
    "max_latency_ms": 0,
    "latency_stddev_ms": 0,
    "jitter_ms": 0,
    "messages_per_second": 0,
    "bytes_per_second": 0.06639563472869739,
    "packet_loss_rate": 0.0,
    "retransmission_rate": 0.0,
    "avg_packet_size": 29,
    "timestamp": "2025-06-24T14:45:06.253613"
  },
  {
    "session_duration": 441.7967143058777,
    "total_messages_sent": 1,
    "total_messages_received": 1,
    "total_bytes_sent": 29,
    "total_bytes_received": 16,
    "total_retransmissions": 0,
    "avg_latency_ms": 0,
    "min_latency_ms": 0,
    "max_latency_ms": 0,
    "latency_stddev_ms": 0,
    "jitter_ms": 0,
    "messages_per_second": 0,
    "bytes_per_second": 0.06564104154623025,
    "packet_loss_rate": 0.0,
    "retransmission_rate": 0.0,
    "avg_packet_size": 29,
    "timestamp": "2025-06-24T14:45:11.274666"
  },
  {
    "session_duration": 446.8114342689514,
    "total_messages_sent": 1,
    "total_messages_received": 1,
    "total_bytes_sent": 29,
    "total_bytes_received": 16,
    "total_retransmissions": 0,
    "avg_latency_ms": 0,
    "min_latency_ms": 0,
    "max_latency_ms": 0,
    "latency_stddev_ms": 0,
    "jitter_ms": 0,
    "messages_per_second": 0,
    "bytes_per_second": 0.06490431189538899,
    "packet_loss_rate": 0.0,
    "retransmission_rate": 0.0,
    "avg_packet_size": 29,
    "timestamp": "2025-06-24T14:45:16.289557"
  },
  {
    "session_duration": 451.8277699947357,
    "total_messages_sent": 1,
    "total_messages_received": 1,
    "total_bytes_sent": 29,
    "total_bytes_received": 16,
    "total_retransmissions": 0,
    "avg_latency_ms": 0,
    "min_latency_ms": 0,
    "max_latency_ms": 0,
    "latency_stddev_ms": 0,
    "jitter_ms": 0,
    "messages_per_second": 0,
    "bytes_per_second": 0.06418371767869095,
    "packet_loss_rate": 0.0,
    "retransmission_rate": 0.0,
    "avg_packet_size": 29,
    "timestamp": "2025-06-24T14:45:21.305935"
  },
  {
    "session_duration": 456.86468148231506,
    "total_messages_sent": 1,
    "total_messages_received": 1,
    "total_bytes_sent": 29,
    "total_bytes_received": 16,
    "total_retransmissions": 0,
    "avg_latency_ms": 0,
    "min_latency_ms": 0,
    "max_latency_ms": 0,
    "latency_stddev_ms": 0,
    "jitter_ms": 0,
    "messages_per_second": 0,
    "bytes_per_second": 0.0634761188206942,
    "packet_loss_rate": 0.0,
    "retransmission_rate": 0.0,
    "avg_packet_size": 29,
    "timestamp": "2025-06-24T14:45:26.342630"
  },
  {
    "session_duration": 461.87737369537354,
    "total_messages_sent": 1,
    "total_messages_received": 1,
    "total_bytes_sent": 29,
    "total_bytes_received": 16,
    "total_retransmissions": 0,
    "avg_latency_ms": 0,
    "min_latency_ms": 0,
    "max_latency_ms": 0,
    "latency_stddev_ms": 0,
    "jitter_ms": 0,
    "messages_per_second": 0,
    "bytes_per_second": 0.06278720835887351,
    "packet_loss_rate": 0.0,
    "retransmission_rate": 0.0,
    "avg_packet_size": 29,
    "timestamp": "2025-06-24T14:45:31.355469"
  },
  {
    "session_duration": 466.92760586738586,
    "total_messages_sent": 1,
    "total_messages_received": 1,
    "total_bytes_sent": 29,
    "total_bytes_received": 16,
    "total_retransmissions": 0,
    "avg_latency_ms": 0,
    "min_latency_ms": 0,
    "max_latency_ms": 0,
    "latency_stddev_ms": 0,
    "jitter_ms": 0,
    "messages_per_second": 0,
    "bytes_per_second": 0.06210810931969208,
    "packet_loss_rate": 0.0,
    "retransmission_rate": 0.0,
    "avg_packet_size": 29,
    "timestamp": "2025-06-24T14:45:36.405698"
  },
  {
    "session_duration": 471.9761941432953,
    "total_messages_sent": 1,
    "total_messages_received": 1,
    "total_bytes_sent": 29,
    "total_bytes_received": 16,
    "total_retransmissions": 0,
    "avg_latency_ms": 0,
    "min_latency_ms": 0,
    "max_latency_ms": 0,
    "latency_stddev_ms": 0,
    "jitter_ms": 0,
    "messages_per_second": 0,
    "bytes_per_second": 0.061443751625618055,
    "packet_loss_rate": 0.0,
    "retransmission_rate": 0.0,
    "avg_packet_size": 29,
    "timestamp": "2025-06-24T14:45:41.454333"
  },
  {
    "session_duration": 477.010454416275,
    "total_messages_sent": 1,
    "total_messages_received": 1,
    "total_bytes_sent": 29,
    "total_bytes_received": 16,
    "total_retransmissions": 0,
    "avg_latency_ms": 0,
    "min_latency_ms": 0,
    "max_latency_ms": 0,
    "latency_stddev_ms": 0,
    "jitter_ms": 0,
    "messages_per_second": 0,
    "bytes_per_second": 0.060795293894231855,
    "packet_loss_rate": 0.0,
    "retransmission_rate": 0.0,
    "avg_packet_size": 29,
    "timestamp": "2025-06-24T14:45:46.488549"
  },
  {
    "session_duration": 482.0277032852173,
    "total_messages_sent": 1,
    "total_messages_received": 1,
    "total_bytes_sent": 29,
    "total_bytes_received": 16,
    "total_retransmissions": 0,
    "avg_latency_ms": 0,
    "min_latency_ms": 0,
    "max_latency_ms": 0,
    "latency_stddev_ms": 0,
    "jitter_ms": 0,
    "messages_per_second": 0,
    "bytes_per_second": 0.0601625060622157,
    "packet_loss_rate": 0.0,
    "retransmission_rate": 0.0,
    "avg_packet_size": 29,
    "timestamp": "2025-06-24T14:45:51.505691"
  },
  {
    "session_duration": 487.0427505970001,
    "total_messages_sent": 1,
    "total_messages_received": 1,
    "total_bytes_sent": 29,
    "total_bytes_received": 16,
    "total_retransmissions": 0,
    "avg_latency_ms": 0,
    "min_latency_ms": 0,
    "max_latency_ms": 0,
    "latency_stddev_ms": 0,
    "jitter_ms": 0,
    "messages_per_second": 0,
    "bytes_per_second": 0.05954300708422853,
    "packet_loss_rate": 0.0,
    "retransmission_rate": 0.0,
    "avg_packet_size": 29,
    "timestamp": "2025-06-24T14:45:56.520871"
  },
  {
    "session_duration": 492.05587553977966,
    "total_messages_sent": 1,
    "total_messages_received": 1,
    "total_bytes_sent": 29,
    "total_bytes_received": 16,
    "total_retransmissions": 0,
    "avg_latency_ms": 0,
    "min_latency_ms": 0,
    "max_latency_ms": 0,
    "latency_stddev_ms": 0,
    "jitter_ms": 0,
    "messages_per_second": 0,
    "bytes_per_second": 0.05893638859323325,
    "packet_loss_rate": 0.0,
    "retransmission_rate": 0.0,
    "avg_packet_size": 29,
    "timestamp": "2025-06-24T14:46:01.533839"
  },
  {
    "session_duration": 497.0702955722809,
    "total_messages_sent": 1,
    "total_messages_received": 1,
    "total_bytes_sent": 29,
    "total_bytes_received": 16,
    "total_retransmissions": 0,
    "avg_latency_ms": 0,
    "min_latency_ms": 0,
    "max_latency_ms": 0,
    "latency_stddev_ms": 0,
    "jitter_ms": 0,
    "messages_per_second": 0,
    "bytes_per_second": 0.0583418173476783,
    "packet_loss_rate": 0.0,
    "retransmission_rate": 0.0,
    "avg_packet_size": 29,
    "timestamp": "2025-06-24T14:46:06.548520"
  },
  {
    "session_duration": 502.1234221458435,
    "total_messages_sent": 1,
    "total_messages_received": 1,
    "total_bytes_sent": 29,
    "total_bytes_received": 16,
    "total_retransmissions": 0,
    "avg_latency_ms": 0,
    "min_latency_ms": 0,
    "max_latency_ms": 0,
    "latency_stddev_ms": 0,
    "jitter_ms": 0,
    "messages_per_second": 0,
    "bytes_per_second": 0.05775470794907801,
    "packet_loss_rate": 0.0,
    "retransmission_rate": 0.0,
    "avg_packet_size": 29,
    "timestamp": "2025-06-24T14:46:11.601512"
  },
  {
    "session_duration": 507.17315340042114,
    "total_messages_sent": 1,
    "total_messages_received": 1,
    "total_bytes_sent": 29,
    "total_bytes_received": 16,
    "total_retransmissions": 0,
    "avg_latency_ms": 0,
    "min_latency_ms": 0,
    "max_latency_ms": 0,
    "latency_stddev_ms": 0,
    "jitter_ms": 0,
    "messages_per_second": 0,
    "bytes_per_second": 0.05717966068739333,
    "packet_loss_rate": 0.0,
    "retransmission_rate": 0.0,
    "avg_packet_size": 29,
    "timestamp": "2025-06-24T14:46:16.651293"
  },
  {
    "session_duration": 512.1910724639893,
    "total_messages_sent": 1,
    "total_messages_received": 1,
    "total_bytes_sent": 29,
    "total_bytes_received": 16,
    "total_retransmissions": 0,
    "avg_latency_ms": 0,
    "min_latency_ms": 0,
    "max_latency_ms": 0,
    "latency_stddev_ms": 0,
    "jitter_ms": 0,
    "messages_per_second": 0,
    "bytes_per_second": 0.05661947892029057,
    "packet_loss_rate": 0.0,
    "retransmission_rate": 0.0,
    "avg_packet_size": 29,
    "timestamp": "2025-06-24T14:46:21.669163"
  },
  {
    "session_duration": 517.2201426029205,
    "total_messages_sent": 1,
    "total_messages_received": 1,
    "total_bytes_sent": 29,
    "total_bytes_received": 16,
    "total_retransmissions": 0,
    "avg_latency_ms": 0,
    "min_latency_ms": 0,
    "max_latency_ms": 0,
    "latency_stddev_ms": 0,
    "jitter_ms": 0,
    "messages_per_second": 0,
    "bytes_per_second": 0.05606895298589492,
    "packet_loss_rate": 0.0,
    "retransmission_rate": 0.0,
    "avg_packet_size": 29,
    "timestamp": "2025-06-24T14:46:26.698231"
  },
  {
    "session_duration": 522.2564494609833,
    "total_messages_sent": 1,
    "total_messages_received": 1,
    "total_bytes_sent": 29,
    "total_bytes_received": 16,
    "total_retransmissions": 0,
    "avg_latency_ms": 0,
    "min_latency_ms": 0,
    "max_latency_ms": 0,
    "latency_stddev_ms": 0,
    "jitter_ms": 0,
    "messages_per_second": 0,
    "bytes_per_second": 0.05552826947813572,
    "packet_loss_rate": 0.0,
    "retransmission_rate": 0.0,
    "avg_packet_size": 29,
    "timestamp": "2025-06-24T14:46:31.734406"
  },
  {
    "session_duration": 527.2711961269379,
    "total_messages_sent": 1,
    "total_messages_received": 1,
    "total_bytes_sent": 29,
    "total_bytes_received": 16,
    "total_retransmissions": 0,
    "avg_latency_ms": 0,
    "min_latency_ms": 0,
    "max_latency_ms": 0,
    "latency_stddev_ms": 0,
    "jitter_ms": 0,
    "messages_per_second": 0,
    "bytes_per_second": 0.055000136262721544,
    "packet_loss_rate": 0.0,
    "retransmission_rate": 0.0,
    "avg_packet_size": 29,
    "timestamp": "2025-06-24T14:46:36.749371"
  },
  {
    "session_duration": 532.3186948299408,
    "total_messages_sent": 1,
    "total_messages_received": 1,
    "total_bytes_sent": 29,
    "total_bytes_received": 16,
    "total_retransmissions": 0,
    "avg_latency_ms": 0,
    "min_latency_ms": 0,
    "max_latency_ms": 0,
    "latency_stddev_ms": 0,
    "jitter_ms": 0,
    "messages_per_second": 0,
    "bytes_per_second": 0.05447863522572545,
    "packet_loss_rate": 0.0,
    "retransmission_rate": 0.0,
    "avg_packet_size": 29,
    "timestamp": "2025-06-24T14:46:41.796676"
  },
  {
    "session_duration": 537.3373181819916,
    "total_messages_sent": 1,
    "total_messages_received": 1,
    "total_bytes_sent": 29,
    "total_bytes_received": 16,
    "total_retransmissions": 0,
    "avg_latency_ms": 0,
    "min_latency_ms": 0,
    "max_latency_ms": 0,
    "latency_stddev_ms": 0,
    "jitter_ms": 0,
    "messages_per_second": 0,
    "bytes_per_second": 0.053969817027902676,
    "packet_loss_rate": 0.0,
    "retransmission_rate": 0.0,
    "avg_packet_size": 29,
    "timestamp": "2025-06-24T14:46:46.815282"
  },
  {
    "session_duration": 542.355667591095,
    "total_messages_sent": 1,
    "total_messages_received": 1,
    "total_bytes_sent": 29,
    "total_bytes_received": 16,
    "total_retransmissions": 0,
    "avg_latency_ms": 0,
    "min_latency_ms": 0,
    "max_latency_ms": 0,
    "latency_stddev_ms": 0,
    "jitter_ms": 0,
    "messages_per_second": 0,
    "bytes_per_second": 0.05347043281774246,
    "packet_loss_rate": 0.0,
    "retransmission_rate": 0.0,
    "avg_packet_size": 29,
    "timestamp": "2025-06-24T14:46:51.833755"
  },
  {
    "session_duration": 547.4043571949005,
    "total_messages_sent": 1,
    "total_messages_received": 1,
    "total_bytes_sent": 29,
    "total_bytes_received": 16,
    "total_retransmissions": 0,
    "avg_latency_ms": 0,
    "min_latency_ms": 0,
    "max_latency_ms": 0,
    "latency_stddev_ms": 0,
    "jitter_ms": 0,
    "messages_per_second": 0,
    "bytes_per_second": 0.05297728573628198,
    "packet_loss_rate": 0.0,
    "retransmission_rate": 0.0,
    "avg_packet_size": 29,
    "timestamp": "2025-06-24T14:46:56.882310"
  },
  {
    "session_duration": 552.4185619354248,
    "total_messages_sent": 1,
    "total_messages_received": 1,
    "total_bytes_sent": 29,
    "total_bytes_received": 16,
    "total_retransmissions": 0,
    "avg_latency_ms": 0,
    "min_latency_ms": 0,
    "max_latency_ms": 0,
    "latency_stddev_ms": 0,
    "jitter_ms": 0,
    "messages_per_second": 0,
    "bytes_per_second": 0.0524964179885624,
    "packet_loss_rate": 0.0,
    "retransmission_rate": 0.0,
    "avg_packet_size": 29,
    "timestamp": "2025-06-24T14:47:01.896554"
  },
  {
    "session_duration": 557.4420897960663,
    "total_messages_sent": 1,
    "total_messages_received": 1,
    "total_bytes_sent": 29,
    "total_bytes_received": 16,
    "total_retransmissions": 0,
    "avg_latency_ms": 0,
    "min_latency_ms": 0,
    "max_latency_ms": 0,
    "latency_stddev_ms": 0,
    "jitter_ms": 0,
    "messages_per_second": 0,
    "bytes_per_second": 0.05202332453533834,
    "packet_loss_rate": 0.0,
    "retransmission_rate": 0.0,
    "avg_packet_size": 29,
    "timestamp": "2025-06-24T14:47:06.920264"
  },
  {
    "session_duration": 562.4672119617462,
    "total_messages_sent": 1,
    "total_messages_received": 1,
    "total_bytes_sent": 29,
    "total_bytes_received": 16,
    "total_retransmissions": 0,
    "avg_latency_ms": 0,
    "min_latency_ms": 0,
    "max_latency_ms": 0,
    "latency_stddev_ms": 0,
    "jitter_ms": 0,
    "messages_per_second": 0,
    "bytes_per_second": 0.05155854747737316,
    "packet_loss_rate": 0.0,
    "retransmission_rate": 0.0,
    "avg_packet_size": 29,
    "timestamp": "2025-06-24T14:47:11.945297"
  },
  {
    "session_duration": 567.499183177948,
    "total_messages_sent": 1,
    "total_messages_received": 1,
    "total_bytes_sent": 29,
    "total_bytes_received": 16,
    "total_retransmissions": 0,
    "avg_latency_ms": 0,
    "min_latency_ms": 0,
    "max_latency_ms": 0,
    "latency_stddev_ms": 0,
    "jitter_ms": 0,
    "messages_per_second": 0,
    "bytes_per_second": 0.051101380302948106,
    "packet_loss_rate": 0.0,
    "retransmission_rate": 0.0,
    "avg_packet_size": 29,
    "timestamp": "2025-06-24T14:47:16.977291"
  },
  {
    "session_duration": 0.0003230571746826172,
    "total_messages_sent": 0,
    "total_messages_received": 0,
    "total_bytes_sent": 0,
    "total_bytes_received": 0,
    "total_retransmissions": 0,
    "messages_per_second": 0,
    "bytes_per_second": 0.0,
    "packet_loss_rate": 0,
    "retransmission_rate": 0,
    "timestamp": "2025-06-24T14:48:04.798562"
  },
  {
    "session_duration": 5.00710129737854,
    "total_messages_sent": 2,
    "total_messages_received": 2,
    "total_bytes_sent": 67,
    "total_bytes_received": 32,
    "total_retransmissions": 0,
    "avg_latency_ms": 23.341655731201172,
    "min_latency_ms": 4.28462028503418,
    "max_latency_ms": 42.398691177368164,
    "latency_stddev_ms": 26.950717986594167,
    "jitter_ms": 38.114070892333984,
    "messages_per_second": 2,
    "bytes_per_second": 13.379410471242027,
    "packet_loss_rate": 0.0,
    "retransmission_rate": 0.0,
    "avg_packet_size": 33.5,
    "timestamp": "2025-06-24T14:48:09.805998"
  },
  {
    "session_duration": 10.058885335922241,
    "total_messages_sent": 3,
    "total_messages_received": 3,
    "total_bytes_sent": 111,
    "total_bytes_received": 48,
    "total_retransmissions": 0,
    "avg_latency_ms": 16.681512196858723,
    "min_latency_ms": 3.361225128173828,
    "max_latency_ms": 42.398691177368164,
    "latency_stddev_ms": 22.276515339940303,
    "jitter_ms": 19.518733024597168,
    "messages_per_second": 0,
    "bytes_per_second": 11.034478260311044,
    "packet_loss_rate": 0.0,
    "retransmission_rate": 0.0,
    "avg_packet_size": 37,
    "timestamp": "2025-06-24T14:48:14.857676"
  },
  {
    "session_duration": 15.109909296035767,
    "total_messages_sent": 3,
    "total_messages_received": 3,
    "total_bytes_sent": 111,
    "total_bytes_received": 48,
    "total_retransmissions": 0,
    "avg_latency_ms": 16.681512196858723,
    "min_latency_ms": 3.361225128173828,
    "max_latency_ms": 42.398691177368164,
    "latency_stddev_ms": 22.276515339940303,
    "jitter_ms": 19.518733024597168,
    "messages_per_second": 0,
    "bytes_per_second": 7.3461192856376005,
    "packet_loss_rate": 0.0,
    "retransmission_rate": 0.0,
    "avg_packet_size": 37,
    "timestamp": "2025-06-24T14:48:19.908258"
  },
  {
    "session_duration": 20.123794317245483,
    "total_messages_sent": 3,
    "total_messages_received": 3,
    "total_bytes_sent": 111,
    "total_bytes_received": 48,
    "total_retransmissions": 0,
    "avg_latency_ms": 16.681512196858723,
    "min_latency_ms": 3.361225128173828,
    "max_latency_ms": 42.398691177368164,
    "latency_stddev_ms": 22.276515339940303,
    "jitter_ms": 19.518733024597168,
    "messages_per_second": 0,
    "bytes_per_second": 5.515748030376628,
    "packet_loss_rate": 0.0,
    "retransmission_rate": 0.0,
    "avg_packet_size": 37,
    "timestamp": "2025-06-24T14:48:24.922486"
  },
  {
    "session_duration": 25.172703504562378,
    "total_messages_sent": 3,
    "total_messages_received": 3,
    "total_bytes_sent": 111,
    "total_bytes_received": 48,
    "total_retransmissions": 0,
    "avg_latency_ms": 16.681512196858723,
    "min_latency_ms": 3.361225128173828,
    "max_latency_ms": 42.398691177368164,
    "latency_stddev_ms": 22.276515339940303,
    "jitter_ms": 19.518733024597168,
    "messages_per_second": 0,
    "bytes_per_second": 4.409474769029234,
    "packet_loss_rate": 0.0,
    "retransmission_rate": 0.0,
    "avg_packet_size": 37,
    "timestamp": "2025-06-24T14:48:29.971348"
  }
]